{
  "id": "fe3e8ab8d78abd82f6f52a4e61c4bdab-212",
  "title": "B5084.pdf",
  "content": " section on \u201cstray dog bite\u201d.\n\u2731  One must go immediately to the health centre or district hospital. It should be left to the doctors to decide upon further treatment.\n\n106\nIf the pet dog has not been vaccinated or has been partially vaccinated, then the \ntreatment may be the same as for stray dog bite. The doctor will decide this and \nhis advice should be followed.\nSnake bite\nIn the case of a snake bite:\n\u2731  A tight bandage should be tied above the level of the \nbite, if it is on the arm or leg. This stops the poison from \nspreading to other parts of the body. The bandage should \nNOT be so tight as to stop the flow of blood completely.. The affected person should be checked to see the colour of the fingers or toes. If the colour changes to dark blue, \nthen the bandage is too tight and must be loosened AT \nONCE.  \n\u2731 One should not make a cut to try and remove the poison.\n\u2731  Since the poison can spread through the blood, the person should not ",
  "source": "B5084.pdf",
  "chunk_index": 212,
  "total_chunks": 324
}