{
  "id": "fe3e8ab8d78abd82f6f52a4e61c4bdab-141",
  "title": "B5084.pdf",
  "content": "sk \nfactors such as tobacco use, unhealthy diet, physical inactivity and excessive use \nof alcohol.\n\n69\nDiabetes\nDiabetes is a chronic condition that occurs when blood glucose levels remain \nabove normal limits. In simple terms, this happens if the body cannot convert the sugars and starches in our food into energy. It can happen to all age groups, but mostly in adults and elderly people. \nRisk factors for diabetes are unhealthy diet, overweight/obesity, family history of \ndiabetes, tobacco use, harmful use of alcohol, and physical inactivity. \nWhat are the symptoms of diabetes?\nEarly symptoms include frequent urination, excessive thirst, constant hunger, weight loss, very dry skin, vision changes and fatigue. But these symptoms often \ngo unnoticed. As a result, the disease may be diagnosed several years after onset, \nonce complications have already arisen. Impaired glucose tolerance and impaired fasting glycaemia are intermediate conditions ",
  "source": "B5084.pdf",
  "chunk_index": 141,
  "total_chunks": 324
}