{
  "id": "fe3e8ab8d78abd82f6f52a4e61c4bdab-134",
  "title": "B5084.pdf",
  "content": "  It occurs in those who have multiple sex partners.\n \nWhat happens when a person has an infection?  \nMost STIs may be asymptomatic, but the following symptoms can occur.  \nMen have:  \n\u2731  Pain or burning sensation while passing urine.  \n\u2731  Watery discharge from the penis which after 2-3 days becomes thick and \nyellowish (pus).\n\u2731  Sudden, severe pain in one testicle.   \n\u2731  Swellings on the penis.\n\u2731  Ulcers on the penis.\nWomen have:\n\u2731  Difficulty in passing urine.\n\u2731  Pus in the urine.\n\u2731  Increased discharge from the vagina that may have a bad smell or may be yellow in colour. Vaginal discharge may be thick, having a foul smell and \nyellow pus.\n\u2731  Itching and pain in the vagina.\n\u2731  Irregular bleeding.\n\u2731  Pain in the lower part of the abdomen.\n\u2731  Infections which lead to sterility (inability to have a child).\nWhat should be done if anyone has the above signs and symptoms?\n\u2731  One should go to the hospital or health centre for investigations and treatment. ",
  "source": "B5084.pdf",
  "chunk_index": 134,
  "total_chunks": 324
}