{
  "id": "fe3e8ab8d78abd82f6f52a4e61c4bdab-297",
  "title": "B5084.pdf",
  "content": " covered the next day and request \nthe participants to look at the relevant topics in the handbook. \nOverview of the Day (starting on Day 2 of the training)\n\u2731  Participants can indicate if they have any questions related to the sessions \ncarried out the day before.\n\u2731  The schedule for the day can be reviewed to answer any questions participants may have.\nSupporting people to be empowered for \nsustainable self-care\nEmpowerment is a process by which people gain control over their lives and make \ntheir own decisions.  It is an internalized process to help people develop skills \nand confidence in making decisions and taking actions accordingly.  To make this \nhappen, people need the right information, appropriate skills and confidence, and continuous supports. To support and facilitate people to empower themselves for self-care, CHW and CV need to provide them with the right information to \nraise their awareness, change their perception about ",
  "source": "B5084.pdf",
  "chunk_index": 297,
  "total_chunks": 324
}